[
    {
        "front": "てんいん",
        "back": "clerk",
        "chapter": "N4 C11"
    },
    {
        "front": "きゃく",
        "back": "customer",
        "chapter": "N4 C11"
    },
    {
        "front": "よやく（する）",
        "back": "reservation / to reserve",
        "chapter": "N4 C11"
    },
    {
        "front": "とまる",
        "back": "to stay",
        "chapter": "N4 C11"
    },
    {
        "front": "～はく",
        "back": "~nights of stay",
        "chapter": "N4 C11"
    },
    {
        "front": "あく",
        "back": "to be free",
        "chapter": "N4 C11"
    },
    {
        "front": "もうしわけありません",
        "back": "I'm terribly sorry",
        "chapter": "N4 C11"
    },
    {
        "front": "いっぱい",
        "back": "full",
        "chapter": "N4 C11"
    },
    {
        "front": "かしこまりました",
        "back": "certainly",
        "chapter": "N4 C11"
    },
    {
        "front": "きせつ",
        "back": "season",
        "chapter": "N4 C11"
    },
    {
        "front": "けしき",
        "back": "scenery",
        "chapter": "N4 C11"
    },
    {
        "front": "おんせん",
        "back": "hot spring",
        "chapter": "N4 C11"
    },
    {
        "front": "おんせんりょかん",
        "back": "japanese style inn with hot  spring",
        "chapter": "N4 C11"
    },
    {
        "front": "こころ",
        "back": "mind; heart",
        "chapter": "N4 C11"
    },
    {
        "front": "リラックスする",
        "back": "to relax",
        "chapter": "N4 C11"
    }
]